README.md
setup.cfg
setup.py
certbot_cpanel.egg-info/PKG-INFO
certbot_cpanel.egg-info/SOURCES.txt
certbot_cpanel.egg-info/dependency_links.txt
certbot_cpanel.egg-info/entry_points.txt
certbot_cpanel.egg-info/requires.txt
certbot_cpanel.egg-info/top_level.txt
certbot_dns_cpanel/__init__.py
certbot_dns_cpanel/authenticator.py
certbot_dns_cpanel/cpanel_apiv2.py